ddopy/__init__.py
ddopy/db/__init__.py
ddopy/db/database_manager.py
ddopy/db/model/__init__.py
ddopy/db/model/base.py
ddopy/db/model/endpoint_url.py
ddopy/http/__init__.py
ddopy/http/http_requester.py
ddopy/http/websocket_proxy.py
ddopy/misc/__init__.py
ddopy/misc/config_manager.py
ddopy/misc/task_manager.py
ddopy/misc/time_controller.py
ddopy-0.1.22.dist-info/LICENSE
ddopy-0.1.22.dist-info/METADATA
ddopy-0.1.22.dist-info/WHEEL
ddopy-0.1.22.dist-info/top_level.txt
ddopy-0.1.22.dist-info/RECORD
