Metadata-Version: 2.1
Name: ddopy
Version: 0.1.22
Summary: A collection of utility functions by Ali Burak Kulakli @ DDOSOFT
Home-page: https://github.com/abkulakli/ddopy
Author: Ali Burak Kulakli
Author-email: kulakli@gmail.com
License: MIT
Classifier: Development Status :: 3 - Alpha
Classifier: Intended Audience :: Developers
Classifier: License :: OSI Approved :: MIT License
Classifier: Programming Language :: Python :: 3
Classifier: Programming Language :: Python :: 3.6
Classifier: Programming Language :: Python :: 3.7
Classifier: Programming Language :: Python :: 3.8
Classifier: Programming Language :: Python :: 3.9
License-File: LICENSE
